map_information_processing_package/__init__.py
map_information_processing_package/my_module.py
map_information_processing_package/sum_package/__init__.py
map_information_processing_package/sum_package/sum_module.py
map_information_processing_package-0.1.dist-info/LICENSE
map_information_processing_package-0.1.dist-info/METADATA
map_information_processing_package-0.1.dist-info/WHEEL
map_information_processing_package-0.1.dist-info/top_level.txt
map_information_processing_package-0.1.dist-info/RECORD
