Metadata-Version: 2.1
Name: map-information-processing-package
Version: 0.1
Summary: My Package for map information processing
Home-page: UNKNOWN
Author: wangsongtao
Author-email: 732639860@qq.com
License: UNKNOWN
Platform: UNKNOWN
License-File: LICENSE
